cantonesedetect/Detector.py
cantonesedetect/DocumentFeatures.py
cantonesedetect/JudgementTypes.py
cantonesedetect/SegmentFeatures.py
cantonesedetect/__init__.py
cantonesedetect/cli.py
cantonesedetect/version.py
cantonesedetect-1.1.2.dist-info/LICENSE
cantonesedetect-1.1.2.dist-info/METADATA
cantonesedetect-1.1.2.dist-info/WHEEL
cantonesedetect-1.1.2.dist-info/entry_points.txt
cantonesedetect-1.1.2.dist-info/top_level.txt
cantonesedetect-1.1.2.dist-info/RECORD
