Metadata-Version: 2.1
Name: cantonesedetect
Version: 1.1.2
Summary: A minimal package that detect Cantonese sentences in Traditional Chinese text.
Author: Chaak Ming Lau, Mingfei Lau and Ann Wai Huen To
License-File: LICENSE
